data_chunker/__init__.py
data_chunker/java_code.py
data_chunker/parser.py
data_chunker-0.0.4.dist-info/METADATA
data_chunker-0.0.4.dist-info/WHEEL
data_chunker-0.0.4.dist-info/licenses/LICENSE
data_chunker-0.0.4.dist-info/RECORD
