Metadata-Version: 2.1
Name: data-chunker
Version: 0.0.4
Summary: Chunks code into a list made up of indexable dictionaries.
Project-URL: Homepage, https://github.com/break-free/data-chunker
Project-URL: Issues, https://github.com/break-free/data-chunker/issues
Author-email: Chris Mills <cmills@breakfreesolutions.com>, Colin Pitawanakwat <cpitawanakwat@breakfreesolutions.com>
License-File: LICENSE
Classifier: License :: OSI Approved :: MIT License
Classifier: Operating System :: OS Independent
Classifier: Programming Language :: Python :: 3
Requires-Python: >=3.10
Requires-Dist: javalang
